cudag/__init__.py
cudag/py.typed
cudag/annotation/__init__.py
cudag/annotation/codegen.py
cudag/annotation/config.py
cudag/annotation/loader.py
cudag/annotation/scaffold.py
cudag/annotation/transcription.py
cudag/cli/__init__.py
cudag/cli/main.py
cudag/cli/new.py
cudag/core/__init__.py
cudag/core/button.py
cudag/core/canvas.py
cudag/core/config.py
cudag/core/coords.py
cudag/core/data_grid.py
cudag/core/dataset.py
cudag/core/distribution.py
cudag/core/drawing.py
cudag/core/fonts.py
cudag/core/generator.py
cudag/core/grid.py
cudag/core/grounding_task.py
cudag/core/icon.py
cudag/core/iconlist_task.py
cudag/core/models.py
cudag/core/random.py
cudag/core/renderer.py
cudag/core/screen.py
cudag/core/scroll_task.py
cudag/core/scrollable_grid.py
cudag/core/state.py
cudag/core/task.py
cudag/core/taskbar.py
cudag/core/text.py
cudag/core/utils.py
cudag/core/verification_task.py
cudag/data/surnames.txt
cudag/modal_apps/__init__.py
cudag/modal_apps/archive.py
cudag/modal_apps/extract.py
cudag/modal_apps/preprocess.py
cudag/modal_apps/upload.py
cudag/preprocessing/__init__.py
cudag/preprocessing/__main__.py
cudag/preprocessing/config.py
cudag/preprocessing/processor.py
cudag/prompts/SYSTEM_PROMPT.txt
cudag/prompts/__init__.py
cudag/prompts/baml_parser.py
cudag/prompts/baml_types.py
cudag/prompts/system.py
cudag/prompts/tools.py
cudag/schemas/filesystem.json
cudag/schemas/test_record.schema.json
cudag/schemas/train_record.schema.json
cudag/server/__init__.py
cudag/server/app.py
cudag/server/services/__init__.py
cudag/server/services/generator.py
cudag/templates/scripts/archive.sh
cudag/templates/scripts/build.sh
cudag/templates/scripts/extract.sh
cudag/templates/scripts/pre-commit.sh
cudag/templates/scripts/production.sh
cudag/templates/scripts/test.sh
cudag/templates/scripts/upload.sh
cudag/templates/scripts/verify.py
cudag/validation/__init__.py
cudag/validation/validate.py
cudag-0.4.1.dist-info/METADATA
cudag-0.4.1.dist-info/WHEEL
cudag-0.4.1.dist-info/entry_points.txt
cudag-0.4.1.dist-info/licenses/LICENSE
cudag-0.4.1.dist-info/RECORD
