Metadata-Version: 2.4
Name: cudag
Version: 0.4.1
Summary: CUDAG - Computer Use Deterministic Augmented Generator framework for building VLM training data generators
Project-URL: Homepage, https://github.com/claimhawk/pypi-cudag
Project-URL: Documentation, https://github.com/claimhawk/pypi-cudag#readme
Project-URL: Repository, https://github.com/claimhawk/pypi-cudag
Project-URL: Issues, https://github.com/claimhawk/pypi-cudag/issues
Author: ClaimHawk Michael
License-Expression: MIT
License-File: LICENSE
Keywords: computer-use,dataset-generation,training-data,vision-language-model,vlm
Classifier: Development Status :: 4 - Beta
Classifier: Intended Audience :: Developers
Classifier: Intended Audience :: Science/Research
Classifier: License :: OSI Approved :: MIT License
Classifier: Operating System :: OS Independent
Classifier: Programming Language :: Python :: 3
Classifier: Programming Language :: Python :: 3.11
Classifier: Programming Language :: Python :: 3.12
Classifier: Programming Language :: Python :: 3.13
Classifier: Topic :: Scientific/Engineering :: Artificial Intelligence
Classifier: Typing :: Typed
Requires-Python: >=3.12
Requires-Dist: click>=8.0
Requires-Dist: fastapi>=0.109.0
Requires-Dist: modal>=0.60.0
Requires-Dist: pillow>=10.0.0
Requires-Dist: pyyaml>=6.0
Requires-Dist: uvicorn>=0.27.0
Provides-Extra: dev
Requires-Dist: mypy>=1.0.0; extra == 'dev'
Requires-Dist: pytest>=7.0.0; extra == 'dev'
Requires-Dist: ruff>=0.1.0; extra == 'dev'
Requires-Dist: types-pyyaml; extra == 'dev'
Provides-Extra: preprocessing
Requires-Dist: numpy>=1.24.0; extra == 'preprocessing'
Requires-Dist: qwen-vl-utils>=0.0.8; extra == 'preprocessing'
Requires-Dist: torch>=2.4.0; extra == 'preprocessing'
Requires-Dist: torchvision>=0.19.0; extra == 'preprocessing'
Requires-Dist: tqdm>=4.65.0; extra == 'preprocessing'
Requires-Dist: transformers>=4.57.0; extra == 'preprocessing'
